originality/__init__.py
originality/cuda_lcs_module.so
originality/lcs.py
originality-0.0.9.dist-info/LICENSE
originality-0.0.9.dist-info/METADATA
originality-0.0.9.dist-info/WHEEL
originality-0.0.9.dist-info/top_level.txt
originality-0.0.9.dist-info/RECORD
