Metadata-Version: 2.1
Name: originality
Version: 0.0.9
Summary: Calculating text originality in Python
Home-page: https://github.com/MihkelLepson/originality
Download-URL: https://github.com/MihkelLepson/originality
Author: Mihkel Lepson
Author-email: mihkel.lepson@ut.ee
License: MIT
Keywords: NLP
Classifier: Programming Language :: Python :: 3
Classifier: License :: OSI Approved :: MIT License
Classifier: Operating System :: OS Independent
Classifier: Environment :: GPU :: NVIDIA CUDA
Requires-Python: >=3.9
License-File: LICENSE
Requires-Dist: numpy >=1.20.0
